{
    "achievements.joins": "<color:#BAD8B6><b>が</b></color> に参加",
    "achievements.joins.description": "<color:#FCE7C8>サーバーに複数回参加します。</color>",
    "achievements.chopping": "<color:#BAD8B6><b>チョッピング</b></color>",
    "achievements.chopping.description": "<color:#FCE7C8>たくさんの木を切り倒します。</color>",
    "achievements.mining": "<color:#BAD8B6><b>採掘</b></color>",
    "achievements.mining.description": "<color:#FCE7C8>進捗するために様々なブロックを採掘します。</color>",
    "achievements.fishing": "<color:#BAD8B6><b>フィッシング</b></color>",
    "achievements.fishing.description": "<color:#FCE7C8>魚などの宝物を捕まえよう。</color>",
    "achievements.mining_coal": "<color:#BAD8B6><b>石炭採掘</b></color>",
    "achievements.mining_coal.description": "<color:#FCE7C8>石炭を大量採集する。</color>",
    "achievements.mining_iron": "<color:#BAD8B6><b>鉄鉱石</b></color>",
    "achievements.mining_iron.description": "<color:#FCE7C8>必要に応じて鉄鉱石を回収する。</color>",
    "achievements.mining_gold": "<color:#BAD8B6><b>金採掘</b></color>",
    "achievements.mining_gold.description": "<color:#FCE7C8>貴重な金鉱石を取得する。</color>",
    "achievements.mining_diamond": "<color:#BAD8B6><b>ダイヤモンド採掘</b></color>",
    "achievements.mining_diamond.description": "<color:#FCE7C8>ダイヤモンド鉱石を見つけて採掘する。</color>",
    "achievements.mining_emerald": "<color:#BAD8B6><b>エメラルド採掘</b></color>",
    "achievements.mining_emerald.description": "<color:#FCE7C8>エメラルド鉱石を発見して抽出する。</color>",
    "achievements.mining_lapis": "<color:#BAD8B6><b>ラピス採掘</b></color>",
    "achievements.mining_lapis.description": "<color:#FCE7C8>あなたのアイテムをエンチャントするにはラピスラズリを採掘してください。</color>",
    "achievements.mining_redstone": "<color:#BAD8B6><b>レッドストーン採掘</b></color>",
    "achievements.mining_redstone.description": "<color:#FCE7C8>装備のためにレッドストーンを集めよう。</color>",
    "achievements.generate_stone": "<color:#BAD8B6><b>石生成</b></color>",
    "achievements.generate_stone.description": "<color:#FCE7C8>石畳の発電機を使って石を生成します。</color>",
    "achievements.generate_coal": "<color:#BAD8B6><b>石炭生成</b></color>",
    "achievements.generate_coal.description": "<color:#FCE7C8>発電機から石炭を作る。</color>",
    "achievements.generate_iron": "<color:#BAD8B6><b>鉄生成</b></color>",
    "achievements.generate_iron.description": "<color:#FCE7C8>発電機から鉄鉱石を生産する。</color>",
    "achievements.generate_gold": "<color:#BAD8B6><b>ゴールド生成</b></color>",
    "achievements.generate_gold.description": "<color:#FCE7C8>発電機から金鉱石を生成する。</color>",
    "achievements.generate_diamond": "<color:#BAD8B6><b>ダイヤモンド生成</b></color>",
    "achievements.generate_diamond.description": "<color:#FCE7C8>ジェネレータを使用してダイヤモンド鉱石を生成します。</color>",
    "achievements.generate_emerald": "<color:#BAD8B6><b>エメラルド生成</b></color>",
    "achievements.generate_emerald.description": "<color:#FCE7C8>発電機からエメラルド鉱石を生産する。</color>",
    "achievements.generate_lapis": "<color:#BAD8B6><b>ラピス生成</b></color>",
    "achievements.generate_lapis.description": "<color:#FCE7C8>発電機からラピス鉱石を生成する。</color>",
    "achievements.generate_redstone": "<color:#BAD8B6><b>レッドストーン</b></color>",
    "achievements.generate_redstone.description": "<color:#FCE7C8>発電機を使ってレッドストーン鉱石を作る。</color>",
    "achievements.farming_carrots": "<color:#BAD8B6><b>ニンジン農業</b></color>",
    "achievements.farming_carrots.description": "<color:#FCE7C8>ニンジンを育て収穫します。</color>",
    "achievements.farming_potatoes": "<color:#BAD8B6><b>ジャガイモ農業</b></color>",
    "achievements.farming_potatoes.description": "<color:#FCE7C8>ジャガイモを育て収穫します。</color>",
    "achievements.farming_beetroots": "<color:#BAD8B6><b>ビートルート農業</b></color>",
    "achievements.farming_beetroots.description": "<color:#FCE7C8>甲虫を育て収穫します。</color>",
    "achievements.farming_melons": "<color:#BAD8B6><b>メロン農業</b></color>",
    "achievements.farming_melons.description": "<color:#FCE7C8>メロンを成長させ収穫します。</color>",
    "achievements.farming_pumpkins": "<color:#BAD8B6><b>カボチャの栽培</b></color>",
    "achievements.farming_pumpkins.description": "<color:#FCE7C8>カボチャを栽培・収穫します。</color>",
    "achievements.farming_wheat": "<color:#BAD8B6><b>小麦栽培</b></color>",
    "achievements.farming_wheat.description": "<color:#FCE7C8>小麦を育て収穫します。</color>",
    "achievements.farming_cactus": "<color:#BAD8B6><b>サボテン農業</b></color>",
    "achievements.farming_cactus.description": "<color:#FCE7C8>成長しサボテンを収穫する。</color>",
    "achievements.farming_sugarcane": "<color:#BAD8B6><b>サトウキビ農業</b></color>",
    "achievements.farming_sugarcane.description": "<color:#FCE7C8>サトウキビを育て収穫します。</color>",
    "achievements.farming_cocoa": "<color:#BAD8B6><b>ココア農業</b></color>",
    "achievements.farming_cocoa.description": "<color:#FCE7C8>カカオ豆を成長・収穫します。</color>"
}
