{
    "achievements.joins": "<color:#BAD8B6><b>se alătură</b></color>",
    "achievements.joins.description": "<color:#FCE7C8>Alătură-te serverului de mai multe ori.</color>",
    "achievements.chopping": "<color:#BAD8B6><b>Decupare</b></color>",
    "achievements.chopping.description": "<color:#FCE7C8>Omite o mulțime de copaci.</color>",
    "achievements.mining": "<color:#BAD8B6><b>Miner</b></color>",
    "achievements.mining.description": "<color:#FCE7C8>Minează diverse blocuri pentru a progresa.</color>",
    "achievements.fishing": "<color:#BAD8B6><b>Pescuitul</b></color>",
    "achievements.fishing.description": "<color:#FCE7C8>Prinde pește și alte comori.</color>",
    "achievements.mining_coal": "<color:#BAD8B6><b>Minerit de cărbune</b></color>",
    "achievements.mining_coal.description": "<color:#FCE7C8>Adună o grămadă de cărbune.</color>",
    "achievements.mining_iron": "<color:#BAD8B6><b>Minerit de fier</b></color>",
    "achievements.mining_iron.description": "<color:#FCE7C8>Colectează minereu de fier pentru nevoile tale.</color>",
    "achievements.mining_gold": "<color:#BAD8B6><b>Minerit de aur</b></color>",
    "achievements.mining_gold.description": "<color:#FCE7C8>Profită de minereul de aur prețios.</color>",
    "achievements.mining_diamond": "<color:#BAD8B6><b>Minerit de diamant</b></color>",
    "achievements.mining_diamond.description": "<color:#FCE7C8>Găsește și minează minereuri de diamant.</color>",
    "achievements.mining_emerald": "<color:#BAD8B6><b>Minerit Emerald</b></color>",
    "achievements.mining_emerald.description": "<color:#FCE7C8>Descoperă și extrage minereul smarald.</color>",
    "achievements.mining_lapis": "<color:#BAD8B6><b>Lapis Mining</b></color>",
    "achievements.mining_lapis.description": "<color:#FCE7C8>Minează lapis lazuli să îți încânte articolele.</color>",
    "achievements.mining_redstone": "<color:#BAD8B6><b>Mining de piatră roșie</b></color>",
    "achievements.mining_redstone.description": "<color:#FCE7C8>Colectează piatra roșie pentru invențiile tale.</color>",
    "achievements.generate_stone": "<color:#BAD8B6><b>Generare Piatră</b></color>",
    "achievements.generate_stone.description": "<color:#FCE7C8>Generează piatră folosind generatorul tău cobblestone.</color>",
    "achievements.generate_coal": "<color:#BAD8B6><b>Generație de cărbune</b></color>",
    "achievements.generate_coal.description": "<color:#FCE7C8>Creează cărbune prin generatorul tău.</color>",
    "achievements.generate_iron": "<color:#BAD8B6><b>Generație de fier</b></color>",
    "achievements.generate_iron.description": "<color:#FCE7C8>Produce minereu de fier din generator.</color>",
    "achievements.generate_gold": "<color:#BAD8B6><b>Generația de aur</b></color>",
    "achievements.generate_gold.description": "<color:#FCE7C8>Generează minereu de aur de la generator.</color>",
    "achievements.generate_diamond": "<color:#BAD8B6><b>Generare diamant</b></color>",
    "achievements.generate_diamond.description": "<color:#FCE7C8>Generează minereu de diamant folosind generatorul tău.</color>",
    "achievements.generate_emerald": "<color:#BAD8B6><b>Generația</b></color>",
    "achievements.generate_emerald.description": "<color:#FCE7C8>Produce smarald ore din generator.</color>",
    "achievements.generate_lapis": "<color:#BAD8B6><b>Generaţia de Lapis</b></color>",
    "achievements.generate_lapis.description": "<color:#FCE7C8>Generează lapis minereu de la generator.</color>",
    "achievements.generate_redstone": "<color:#BAD8B6><b>Generare Piatră roșie</b></color>",
    "achievements.generate_redstone.description": "<color:#FCE7C8>Creează minereu de piatră roșie folosind generatorul tău.</color>",
    "achievements.farming_carrots": "<color:#BAD8B6><b>Ferma Morcov</b></color>",
    "achievements.farming_carrots.description": "<color:#FCE7C8>Mărește și recoltează morcovi.</color>",
    "achievements.farming_potatoes": "<color:#BAD8B6><b>Cartofi Fermieri</b></color>",
    "achievements.farming_potatoes.description": "<color:#FCE7C8>măreşte şi recoltează cartofi.</color>",
    "achievements.farming_beetroots": "<color:#BAD8B6><b>Agricultură cu Beetroot</b></color>",
    "achievements.farming_beetroots.description": "<color:#FCE7C8>Mărește și recoltează gândaci.</color>",
    "achievements.farming_melons": "<color:#BAD8B6><b>Ferma Melon</b></color>",
    "achievements.farming_melons.description": "<color:#FCE7C8>Mărește și recoltează pepeni.</color>",
    "achievements.farming_pumpkins": "<color:#BAD8B6><b>Ferma Dovleac</b></color>",
    "achievements.farming_pumpkins.description": "<color:#FCE7C8>Mărește și recoltează pompe.</color>",
    "achievements.farming_wheat": "<color:#BAD8B6><b>Agricultură de grâu</b></color>",
    "achievements.farming_wheat.description": "<color:#FCE7C8>Mărește și recoltează grâu.</color>",
    "achievements.farming_cactus": "<color:#BAD8B6><b>Agricultură Cactus</b></color>",
    "achievements.farming_cactus.description": "<color:#FCE7C8>Mărește și recoltează cacti.</color>",
    "achievements.farming_sugarcane": "<color:#BAD8B6><b>Urme Fermiere</b></color>",
    "achievements.farming_sugarcane.description": "<color:#FCE7C8>Mărește și recoltează trestie de zahăr.</color>",
    "achievements.farming_cocoa": "<color:#BAD8B6><b>Coca-Ferma</b></color>",
    "achievements.farming_cocoa.description": "<color:#FCE7C8>Mărește și recoltează boabe de cacao.</color>",
    "achievement.level_up": "Ați deblocat <color:#FFD700>%achievement%</color> la nivelul <color:#FFD700>%level%</color>.",
    "achievements.building": "<color:#BAD8B6><b>Construire</b></color>",
    "achievements.building.description": "<color:#FCE7C8>Construiește și îmbunătățește-ți structurile pentru a-ți dezvolta tărâmul.</color>",
    "achievements.farming_bamboo": "<color:#BAD8B6><b>Agricultură cu bambus</b></color>",
    "achievements.farming_bamboo.description": "<color:#FCE7C8>Mărește și recoltează bambus pentru resurse nesfârșite.</color>",
    "achievements.farming_nether_wart": "<color:#BAD8B6><b>Îmbrăcăminte caldă</b></color>",
    "achievements.farming_nether_wart.description": "<color:#FCE7C8>Mărește și recoltează negi pentru bere și tranzacționare.</color>",
    "achievements.farming_twerk": "<color:#BAD8B6><b>Twerk Farming</b></color>",
    "achievements.farming_twerk.description": "<color:#FCE7C8>Folosește arta dansării pentru a accelera creșterea culturilor.</color>",
    "achievements.kills": "<color:#BAD8B6><b>Ucide</b></color>",
    "achievements.kills.description": "<color:#FCE7C8>Înfrânge diverse muchii pentru a-ți dovedi capacitatea de luptă.</color>",
    "achievements.kills_zombies": "<color:#BAD8B6><b>Zombie Hunter</b></color>",
    "achievements.kills_zombies.description": "<color:#FCE7C8>Depuneți cârpe de zombi înainte de a vă infecta lumea.</color>",
    "achievements.kills_skeletons": "<color:#BAD8B6><b>Skeleton Slayer</b></color>",
    "achievements.kills_skeletons.description": "<color:#FCE7C8>Învinge scheletele și evită săgețile.</color>",
    "achievements.kills_creepers": "<color:#BAD8B6><b>Exterminator Creeper</b></color>",
    "achievements.kills_creepers.description": "<color:#FCE7C8>Oprește creeții înainte de a arunca în aer totul!</color>",
    "achievements.kills_spiders": "<color:#BAD8B6><b>Exterminator păianjen</b></color>",
    "achievements.kills_spiders.description": "<color:#FCE7C8>Ai grija de cremenele crawilor care se strâmbesc în întuneric.</color>",
    "achievements.kills_chickens": "<color:#BAD8B6><b>Găină Chef</b></color>",
    "achievements.kills_chickens.description": "<color:#FCE7C8>Vână găini pentru penele și carnea lor.</color>",
    "achievements.kills_cows": "<color:#BAD8B6><b>Vacă Cull</b></color>",
    "achievements.kills_cows.description": "<color:#FCE7C8>Vaci pentru piele și carne de vită.</color>",
    "achievements.kills_pigs": "<color:#BAD8B6><b>Porc Slayer</b></color>",
    "achievements.kills_pigs.description": "<color:#FCE7C8>Dă jos porcii pentru a obține carne delicioasă.</color>",
    "achievements.kills_sheep": "<color:#BAD8B6><b>Oi Shearer... sau Slayer?</b></color>",
    "achievements.kills_sheep.description": "<color:#FCE7C8>Shear or slăbește oile pentru lână și muton.</color>",
    "achievements.kills_wolves": "<color:#BAD8B6><b>Wolf Hunter</b></color>",
    "achievements.kills_wolves.description": "<color:#FCE7C8>Subdatorarea lupilor sălbatici îți fac bine pământurile.</color>",
    "achievements.kills_ocelots": "<color:#BAD8B6><b>Ocelot Tamer... sau Hunter?</b></color>",
    "achievements.kills_ocelots.description": "<color:#FCE7C8>Ursue ocelots pentru loot rar. Sau îmblânzește-le ca animale de companie!</color>",
    "achievements.kills_horses": "<color:#BAD8B6><b>Cartier</b></color>",
    "achievements.kills_horses.description": "<color:#FCE7C8>Vână cai pentru piele, deși ar putea strica câteva inimi.</color>",
    "achievements.kills_rabbits": "<color:#BAD8B6><b>Rabbit Hunter</b></color>",
    "achievements.kills_rabbits.description": "<color:#FCE7C8>Mergeti dupa iepuri pentru a aduna piele si mancare.</color>",
    "achievements.kills_llamas": "<color:#BAD8B6><b>Llama Slayer</b></color>",
    "achievements.kills_llamas.description": "<color:#FCE7C8>Fii atent(ă) la scutul lor în timp ce le dai jos.</color>",
    "achievements.kills_turtles": "<color:#BAD8B6><b>Terminator Turtle</b></color>",
    "achievements.kills_turtles.description": "<color:#FCE7C8>Vânătoare de țestoase, dar uită-te la scoici. Pot fi dure!</color>"
}
