{
    "achievements.joins": "<color:#BAD8B6><b>Betreedt</b></color>",
    "achievements.joins.description": "<color:#FCE7C8>Meestal lid worden van de server.</color>",
    "achievements.chopping": "<color:#BAD8B6><b>Eformat@@1 Snuffelen</b></color>",
    "achievements.chopping.description": "<color:#FCE7C8>Veel bomen omhakken.</color>",
    "achievements.mining": "<color:#BAD8B6><b>Mijnbouw</b></color>",
    "achievements.mining.description": "<color:#FCE7C8>Mijn verschillende blokken om verder te gaan.</color>",
    "achievements.fishing": "<color:#BAD8B6><b>Vissen</b></color>",
    "achievements.fishing.description": "<color:#FCE7C8>Vang vis en andere schatten.</color>",
    "achievements.mining_coal": "<color:#BAD8B6><b>Kool Mijnbouw</b></color>",
    "achievements.mining_coal.description": "<color:#FCE7C8>Verzamel voldoende steenkool.</color>",
    "achievements.mining_iron": "<color:#BAD8B6><b>IJzer Mijning</b></color>",
    "achievements.mining_iron.description": "<color:#FCE7C8>Verzamel ijzererts voor jouw behoeften.</color>",
    "achievements.mining_gold": "<color:#BAD8B6><b>Gouden Mijning</b></color>",
    "achievements.mining_gold.description": "<color:#FCE7C8>Verkrijg de kostbare gouden erts.</color>",
    "achievements.mining_diamond": "<color:#BAD8B6><b>Diamanten Mijning</b></color>",
    "achievements.mining_diamond.description": "<color:#FCE7C8>Vind en delf diamanten erts.</color>",
    "achievements.mining_emerald": "<color:#BAD8B6><b>Smaragd Mijning</b></color>",
    "achievements.mining_emerald.description": "<color:#FCE7C8>Ontdek en pak smaragd erts.</color>",
    "achievements.mining_lapis": "<color:#BAD8B6><b>Lapis Mijnbouw</b></color>",
    "achievements.mining_lapis.description": "<color:#FCE7C8>Mijn lapis lazuli om uw artikelen te betoveren.</color>",
    "achievements.mining_redstone": "<color:#BAD8B6><b>Redstone Mijning</b></color>",
    "achievements.mining_redstone.description": "<color:#FCE7C8>Verzamel redstone voor jouw contrapties.</color>",
    "achievements.generate_stone": "<color:#BAD8B6><b>Steen Generatie</b></color>",
    "achievements.generate_stone.description": "<color:#FCE7C8>Genereer steen met je keistenen generator.</color>",
    "achievements.generate_coal": "<color:#BAD8B6><b>Kool Generatie</b></color>",
    "achievements.generate_coal.description": "<color:#FCE7C8>Creëer steenkool met de generator.</color>",
    "achievements.generate_iron": "<color:#BAD8B6><b>Ijzeren Generatie</b></color>",
    "achievements.generate_iron.description": "<color:#FCE7C8>Produceer ijzererts van de generator.</color>",
    "achievements.generate_gold": "<color:#BAD8B6><b>Gouden Generatie</b></color>",
    "achievements.generate_gold.description": "<color:#FCE7C8>Genereer goud erts van de generator.</color>",
    "achievements.generate_diamond": "<color:#BAD8B6><b>Diamanten Generatie</b></color>",
    "achievements.generate_diamond.description": "<color:#FCE7C8>Genereer diamanten erts met behulp van uw generator.</color>",
    "achievements.generate_emerald": "<color:#BAD8B6><b>Smaragd Generatie</b></color>",
    "achievements.generate_emerald.description": "<color:#FCE7C8>Produce emerald ore from the generator.</color>",
    "achievements.generate_lapis": "<color:#BAD8B6><b>Lapis Generatie</b></color>",
    "achievements.generate_lapis.description": "<color:#FCE7C8>Genereer lapis erts van de generator.</color>",
    "achievements.generate_redstone": "<color:#BAD8B6><b>Redstone Generatie</b></color>",
    "achievements.generate_redstone.description": "<color:#FCE7C8>Maak redstone-erts met behulp van je generator.</color>",
    "achievements.farming_carrots": "<color:#BAD8B6><b>Landbouw</b></color>",
    "achievements.farming_carrots.description": "<color:#FCE7C8>Groei en oogst wortels.</color>",
    "achievements.farming_potatoes": "<color:#BAD8B6><b>Aardappel Landbouw</b></color>",
    "achievements.farming_potatoes.description": "<color:#FCE7C8>groeit en oogst aardappelen.</color>",
    "achievements.farming_beetroots": "<color:#BAD8B6><b>Ketroot Landbouw</b></color>",
    "achievements.farming_beetroots.description": "<color:#FCE7C8>Groei en oogst bietroots.</color>",
    "achievements.farming_melons": "<color:#BAD8B6><b>Meloen Landbouw</b></color>",
    "achievements.farming_melons.description": "<color:#FCE7C8>Groei en oogst meloenen.</color>",
    "achievements.farming_pumpkins": "<color:#BAD8B6><b>Pompoen Landbouw</b></color>",
    "achievements.farming_pumpkins.description": "<color:#FCE7C8>Groei en oogst pompoen.</color>",
    "achievements.farming_wheat": "<color:#BAD8B6><b>Tarwe Landbouw</b></color>",
    "achievements.farming_wheat.description": "<color:#FCE7C8>Groei en oogst tarwe.</color>",
    "achievements.farming_cactus": "<color:#BAD8B6><b>Cactus Landbouw</b></color>",
    "achievements.farming_cactus.description": "<color:#FCE7C8>Groei en oogst cactief.</color>",
    "achievements.farming_sugarcane": "<color:#BAD8B6><b>Suikerriet kweek</b></color>",
    "achievements.farming_sugarcane.description": "<color:#FCE7C8>Groei en oogst suikerriet.</color>",
    "achievements.farming_cocoa": "<color:#BAD8B6><b>Cocoa Landbouw</b></color>",
    "achievements.farming_cocoa.description": "<color:#FCE7C8>Groei en oogst cacaobonen.</color>"
}
